wifi_emulator/__init__.py
wifi_emulator/__main__.py
wifi_emulator/gui.py
wifi_emulator/install_deb.py
wifi_emulator/wifi-emulator_0.1.3_all.deb
wifi_emulator-0.1.3.dist-info/METADATA
wifi_emulator-0.1.3.dist-info/WHEEL
wifi_emulator-0.1.3.dist-info/entry_points.txt
wifi_emulator-0.1.3.dist-info/top_level.txt
wifi_emulator-0.1.3.dist-info/RECORD
