Metadata-Version: 2.4
Name: wifi-emulator
Version: 0.1.3
Summary: WiFi emulator and attack lab GUI for Kali Linux
Author-email: Kaled Aljebur <kaled.aljebur@gmail.com>
Project-URL: Homepage, https://github.com/kaledaljebur/wifi-emulator
Project-URL: Issues, https://github.com/kaledaljebur/wifi-emulator/issues
Requires-Python: >=3.8
